django_gmailapi_json_backend-1.12.dist-info/licenses/LICENSE
gmailapi_backend/__init__.py
gmailapi_backend/service.py
django_gmailapi_json_backend-1.12.dist-info/METADATA
django_gmailapi_json_backend-1.12.dist-info/WHEEL
django_gmailapi_json_backend-1.12.dist-info/top_level.txt
django_gmailapi_json_backend-1.12.dist-info/RECORD
