Metadata-Version: 2.4
Name: django-gmailapi-json-backend
Version: 1.12
Summary: Email backend for Django which sends email via the Gmail API through a JSON credential
Home-page: https://github.com/innoveit/django-gmailapi-json-backend
Author: Innove
Author-email: info@innove.it
Project-URL: Bug Tracker, https://github.com/innoveit/django-gmailapi-json-backend
Classifier: Programming Language :: Python :: 3
Classifier: Programming Language :: Python :: 3 :: Only
Classifier: Programming Language :: Python :: 3.12
Classifier: License :: OSI Approved :: MIT License
Classifier: Operating System :: OS Independent
Requires-Python: >=3.12
License-File: LICENSE
Requires-Dist: django>=4.2
Requires-Dist: google-api-python-client>=2.0
Requires-Dist: google-auth-httplib2>=0.2
Requires-Dist: google-auth-oauthlib>=1.2
Dynamic: license-file
